imlo/__init__.py
imlo/transliterate/__init__.py
imlo/transliterate/charmap.py
imlo/transliterate/core.py
imlo-0.1.1.dist-info/LICENSE
imlo-0.1.1.dist-info/METADATA
imlo-0.1.1.dist-info/WHEEL
imlo-0.1.1.dist-info/top_level.txt
imlo-0.1.1.dist-info/RECORD
