Metadata-Version: 2.1
Name: imlo
Version: 0.1.1
Summary: Imlo package
Home-page: https://github.com/imlouz/imlo
Author: Imlo Developers
Author-email: imloloyihasi@gmail.com
License: GPL-3.0
Platform: UNKNOWN
